{
    "course_data": {
        "action": "editar",
        "id_curso": "4",
        "modulos_a_eliminar": "",
        "nombre_curso": "Diplomado de Testing Avanzado 2",
        "descripcion": "fdsfsdf",
        "tipo_curso": "charla",
        "nivel_curso": "inicial",
        "inicio_mes": "2026-03-02",
        "fecha_finalizacion": "2026-03-26T16:53",
        "tiempo_asignado": "3",
        "horario_inicio": "16:53:00",
        "horario_fin": "21:53:00",
        "dias_clase": [
            "martes"
        ],
        "costo": "60.33",
        "horas_cronologicas": "3",
        "limite_inscripciones": "60",
        "conocimientos_previos": "asdasd",
        "requerimientos_implementos": "asdad",
        "desempe\u00f1o_al_concluir": "asdad",
        "promotor": "2",
        "estado": "1",
        "modulos": {
            "4": {
                "id_modulo": "4",
                "nombre_modulo": "asdasd",
                "numero": "1",
                "contenido": [
                    "dasda"
                ],
                "actividad": "asdasd",
                "instrumento": "adasd"
            }
        },
        "config_firmas": {
            "1": {
                "id_cargo_firmante": "2"
            },
            "2": {
                "id_cargo_firmante": "1"
            },
            "3": {
                "id_cargo_firmante": ""
            },
            "4": {
                "id_cargo_firmante": ""
            },
            "5": {
                "id_cargo_firmante": "",
                "usar_promotor_curso": "1"
            },
            "6": {
                "id_cargo_firmante": ""
            }
        }
    },
    "modules_edit": [
        {
            "id_modulo": 4,
            "id_curso": "4",
            "nombre_modulo": "asdasd",
            "contenido": "[dasda]",
            "numero": "1",
            "actividad": "asdasd",
            "instrumento": "adasd"
        }
    ],
    "modules_new": [],
    "modules_delete": ""
}